codebase_dump/__init__.py
codebase_dump/_version.py
codebase_dump/app.py
codebase_dump/core/__init__.py
codebase_dump/core/audit_api_uploader.py
codebase_dump/core/codebase_analysis.py
codebase_dump/core/ignore_patterns_manager.py
codebase_dump/core/models.py
codebase_dump/core/output_formatter.py
codebase_dump-0.6.0.dist-info/LICENSE
codebase_dump-0.6.0.dist-info/METADATA
codebase_dump-0.6.0.dist-info/WHEEL
codebase_dump-0.6.0.dist-info/entry_points.txt
codebase_dump-0.6.0.dist-info/top_level.txt
codebase_dump-0.6.0.dist-info/RECORD
