Metadata-Version: 2.1
Name: codebase-dump
Version: 0.6.0
Summary: Parse your repository into single-file prompt, so you can use it as an LLM input.
Author: Mirek Stanek, Kamil Stanuch
Author-email: mirek@practicalengineering.management, kamil@stanuch.eu
Requires-Python: >=3.7
License-File: LICENSE
Requires-Dist: tiktoken
Requires-Dist: gitignore-parser
Provides-Extra: dev
Requires-Dist: pytest; extra == "dev"
Requires-Dist: twine; extra == "dev"
